[{"categories":[{"name":"THE 50 STATES","questions":[{"clue":"The 2 states that begin with \"S\" each have this word in their name","answer":"South","value":100,"daily_double":false,"type":"text"},{"clue":"The name of this state comes from the French for \"green mountain\"","answer":"Vermont","value":200,"daily_double":false,"type":"text"},{"clue":"In this state, you can visit Watchaug Pond, Weekapaug Point, & Woonsocket Hill","answer":"Rhode Island","value":300,"daily_double":false,"type":"text"},{"clue":"It's the only state to border only 1 other state","answer":"Maine","value":400,"daily_double":false,"type":"text"},{"clue":"State in which RR tracks from the east & west joined to form the 1st Transcontinental Railroad","answer":"Utah","value":500,"daily_double":false,"type":"text"}]},{"name":"PUBLISHING","questions":[{"clue":"Street Chopper & Dirt Rider are magazines devoted to this","answer":"motorcycles","value":100,"daily_double":false,"type":"text"},{"clue":"To the chagrin of critics, a British publisher has updated this 1901 Beatrix Potter classic","answer":"(The Tale of) Peter Rabbit","value":200,"daily_double":false,"type":"text"},{"clue":"As in the U.S., the weekly magazine with the largest circulation in the U.K. lists these","answer":"television programs","value":300,"daily_double":false,"type":"text"},{"clue":"\"The making of McPaper\", by Peter Prichard, is the study of how this 5-year-old paper came to be","answer":"USA Today","value":400,"daily_double":false,"type":"text"},{"clue":"Newspaper that got N. American rights to the Sept. 1987 story of separating West German Siamese twins","answer":"The National Enquirer","value":500,"daily_double":false,"type":"text"}]},{"name":"JADE","questions":[{"clue":"World Book says jade carving reached its peak during this Chinese dynasty, 1368-1644","answer":"the Ming Dynasty","value":100,"daily_double":false,"type":"text"},{"clue":"Jade was called \"stone of the loins\" for its purported power to cure a ailments of these renal organs","answer":"the kidneys","value":200,"daily_double":false,"type":"text"},{"clue":"The only 2 minerals classified as jade, nephrite & jadeite, are chiefly green & this color","answer":"white","value":300,"daily_double":false,"type":"text"},{"clue":null,"answer":null,"value":null,"daily_double":false},{"clue":null,"answer":null,"value":null,"daily_double":false}]},{"name":"MUSICAL MILES","questions":[{"clue":"In a '60s song, this folk-singing trio was \"500 Miles\" away from home","answer":"Peter, Paul and Mary","value":100,"daily_double":false,"type":"text"},{"clue":"The distance Albert Hammond was from L.A. in 1975","answer":"99 Miles","value":200,"daily_double":false,"type":"text"},{"clue":"On their \"sell out\" album they could see for miles","answer":"the Who","value":300,"daily_double":false,"type":"text"},{"clue":"Son of a dentist, he went to Juilliard to study trumpet","answer":"Miles Davis","value":400,"daily_double":false,"type":"text"},{"clue":"At the end of this song, Shep & the Limelights said, \"I'm not a thousand miles away\"","answer":"\"Daddy's Home\"","value":500,"daily_double":false,"type":"text"}]},{"name":"PHILOSOPHY","questions":[{"clue":null,"answer":null,"value":null,"daily_double":false},{"clue":"This branch of philosophy is concerned with deductive & inductive reasoning","answer":"logic","value":200,"daily_double":false,"type":"text"},{"clue":"Guinness calls this Greek lamp-carrying philosopher a \"famous cynic\"","answer":"Diogenes","value":300,"daily_double":false,"type":"text"},{"clue":"John Locke believed that the mind at birth was a \"tabula rasa\", which translates to this","answer":"a blank slate","value":400,"daily_double":false,"type":"text"},{"clue":"Study of being abs reality, its name came from an \"after physics\" treatise by Aristotle","answer":"metaphysics","value":500,"daily_double":false,"type":"text"}]},{"name":"ROYS & RAYS","questions":[{"clue":"He's played a cop in \"The French Connection\", \"The 7-Ups\", & \"Blue Thunder\"","answer":"Roy Scheider","value":100,"daily_double":false,"type":"text"},{"clue":"This broadcasting duo's last names are Elliot & Goulding","answer":"Bob & Ray","value":200,"daily_double":false,"type":"text"},{"clue":"MacGregor was the real last name of this outlaw, the \"Robin Hood of Scotland\"","answer":"Rob Roy","value":300,"daily_double":false,"type":"text"},{"clue":"[IMAGE CLUE]<br \/>Singer of the following 1956 hit:\"Just walking in the rain \/ Gettin' soakin' wet\"","answer":"Johnnie Ray","value":800,"daily_double":true,"type":"text"},{"clue":"Marine zoologist at U. of Wash. from 1945-72, head of AEC from '73-75, & Governor of Wash. '77-81","answer":"Dixy Lee Ray","value":500,"daily_double":false,"type":"text"}]}],"final":{"category":"AFRICA","clue":"1 of 3 countries that make up the \"horn\" of Africa","answer":"Ethiopia, Somalia, or Djibouti"}},{"categories":[{"name":"PRESIDENTS","questions":[{"clue":"He was named after King Richard the Lion-hearted","answer":"Nixon","value":200,"daily_double":false,"type":"text"},{"clue":"It's who party boss Mark Hanna meant when he said, \"Now look, that damned cowboy is President\"","answer":"Teddy Roosevelt","value":400,"daily_double":false,"type":"text"},{"clue":"The S.S. Mayaguez was seized by Cambodia but recaptured by U.S. Marines during his administration","answer":"Gerald Ford","value":600,"daily_double":false,"type":"text"},{"clue":"After killing Pres. Garfield, Charles Guiteau wrote to this man, \"I presume you appreciate it\"","answer":"Chester Arthur","value":800,"daily_double":false,"type":"text"},{"clue":"In 1848 he became the last slaveholder to be elected president","answer":"Zachary Taylor","value":1000,"daily_double":false,"type":"text"}]},{"name":"THEATER","questions":[{"clue":"Alexandre Dumas, pere wrote a play about this emperor, whom his father had served as a general","answer":"Napoleon","value":200,"daily_double":false,"type":"text"},{"clue":"D. Sutherland was Humbert Humbert in play based on this book, which stopped humming after 12 performances","answer":"Lolita","value":400,"daily_double":false,"type":"text"},{"clue":"1 of 2 Greek dramatists who electrified audiences with plays called \"Electra\" circa 413 B.C.","answer":"Sophocles (or Euripides)","value":600,"daily_double":false,"type":"text"},{"clue":"The English comedy of manners flourished during this era, while Charles II reigned","answer":"Restoration","value":800,"daily_double":false,"type":"text"},{"clue":"A sailor doll laughs maniacally & Milo dies saying, \"Game, set & match!\" at end of this mystery","answer":"Sleuth","value":1000,"daily_double":false,"type":"text"}]},{"name":"9-LETTER WORDS","questions":[{"clue":"What an optometrist might make of himself by wearing a lampshade at a party","answer":"a spectacle","value":200,"daily_double":false,"type":"text"},{"clue":"An official place to live, or an official period of training for a medical specialist","answer":"a residence","value":400,"daily_double":false,"type":"text"},{"clue":"A type of dramatic monologue","answer":"soliloquy","value":600,"daily_double":false,"type":"text"},{"clue":"From Latin \"to check\", it's a formal censure","answer":"a reprimand","value":800,"daily_double":false,"type":"text"},{"clue":"A northern grouse with feathered feet; the 1st letter, a \"P\", is silent","answer":"a ptarmigan","value":1000,"daily_double":false,"type":"text"}]},{"name":"BIBLICAL QUOTES","questions":[{"clue":"Jesus said to the adulteress, \"neither do I condemn thee: go, &...\" do this","answer":"sin no more","value":200,"daily_double":false,"type":"text"},{"clue":"Trying graciously to refuse the job, he told God, \"I am slow of speech, & of a slow tongue\"","answer":"Moses","value":400,"daily_double":false,"type":"text"},{"clue":"The women of Israel said he \"hath slain... his ten thousands\" when he'd only killed 1 person","answer":"David","value":1200,"daily_double":true,"type":"text"},{"clue":"He wrote Timothy, \"We brought nothing into this world, & it is certain we can carry nothing out\"","answer":"Paul","value":800,"daily_double":false,"type":"text"},{"clue":null,"answer":null,"value":null,"daily_double":false}]},{"name":"ISLANDS","questions":[{"clue":"Saint-Pierre & Miquelon are all that's left of this country's colonial empire in Canada","answer":"France","value":200,"daily_double":false,"type":"text"},{"clue":"Largest of the Greater Antilles, this island's people call it \"the pearl of the Antilles\"","answer":"Cuba","value":400,"daily_double":false,"type":"text"},{"clue":"While Taiwan is the island's Chinese name, Portuguese explorers called it this","answer":"Formosa","value":600,"daily_double":false,"type":"text"},{"clue":"At 90%, this smallest Australian state has the highest % of Australian-born people","answer":"Tasmania","value":1600,"daily_double":true,"type":"text"},{"clue":"These islands were the only British territory occupied by the Germans in WWII","answer":"Channel Islands","value":1000,"daily_double":false,"type":"text"}]},{"name":"TELEVISION HISTORY","questions":[{"clue":"This famous NBC news team 1st worked together at the 1956 Republican Covention","answer":"Huntley & Brinkley","value":200,"daily_double":false,"type":"text"},{"clue":"During the 1968-69 season, this comedian's Christmas special got a higher rating than the Super Bowl","answer":"Bob Hope","value":400,"daily_double":false,"type":"text"},{"clue":"In October 1976, she became the 1st network news anchorwoman","answer":"Barbara Walters","value":600,"daily_double":false,"type":"text"},{"clue":"From 1950-53, this post-WWII economic policy was featured in a weekly prime time show","answer":"the Marshall Plan","value":800,"daily_double":false,"type":"text"},{"clue":"Kennedy's FCC chairman who gave the famous \"Vast Wasteland\" speech in 1961","answer":"Newton Minow","value":1000,"daily_double":false,"type":"text"}]}],"final":{"category":"AFRICA","clue":"1 of 3 countries that make up the \"horn\" of Africa","answer":"Ethiopia, Somalia, or Djibouti"}}]