{"contestants":[{"name":"Player1","score":0},{"name":"Player2","score":0},{"name":"Player3","score":0}],"categories":[{"name":"ANCIENT ROME","questions":[{"clue":"During the siege of a city, the Romans might use an aries, one of these, to knock down the city's walls","answer":"a battering ram","value":400,"daily_double":false,"type":"text"},{"clue":"Ostia, a town lying 15 miles from Rome on the mouth of this river, served as Rome's port","answer":"the Tiber","value":800,"daily_double":false,"type":"text"},{"clue":"This government body met in the Curia Julia, a rectangular brick building situated in the Forum","answer":"the Senate","value":1200,"daily_double":false,"type":"text"},{"clue":"On June 9, 68 A.D. this emperor told the centurion who'd come to arrest him, \"this is fidelity\" as he died by his own hand","answer":"Nero","value":1600,"daily_double":false,"type":"text"},{"clue":"[IMAGE CLUE]<br \/>(Jimmy of the Clue Crew shows a map on the monitor.)  An emperor's visit to Britain in 122 A.D. led to the building of this defensive barrier that remained effective for almost 300 years","answer":"Hadrian's Wall","value":2000,"daily_double":false,"type":"text"}]},{"name":"THE \"I\"s HAVE IT","questions":[{"clue":"A court may give a reluctant witness this protection \"from prosecution\"","answer":"immunity","value":400,"daily_double":false,"type":"text"},{"clue":"Any violation of the rules","answer":"infraction","value":800,"daily_double":false,"type":"text"},{"clue":null,"answer":null,"value":null,"daily_double":false},{"clue":null,"answer":null,"value":null,"daily_double":false},{"clue":null,"answer":null,"value":null,"daily_double":false}]},{"name":"ANATOMY","questions":[{"clue":"Of the 14 facial bones, it's the only movable one","answer":"the mandible","value":400,"daily_double":false,"type":"text"},{"clue":"The shape of this pocket below the skin's surface determines whether hair will be curly, wavy or straight","answer":"the hair follicle","value":800,"daily_double":false,"type":"text"},{"clue":"The sigmoid section of this part of the digestive tract is named for its \"S\" shape","answer":"the colon","value":1200,"daily_double":true,"type":"text"},{"clue":"Not to be confused with the trapezius muscle, the trapezium & trapezoid are 2 of the 8 carpal bones found in this joint","answer":"the wrist","value":1600,"daily_double":false,"type":"text"},{"clue":"This cone-shaped area at the base of the brain regulates many activities, including the wake-sleep cycle","answer":"the hypothalamus","value":2000,"daily_double":false,"type":"text"}]},{"name":"SOAP BRANDS DEFINED","questions":[{"clue":"Molten, fluid rock","answer":"Lava","value":400,"daily_double":false,"type":"text"},{"clue":"Hawk's opposite, symbolically","answer":"Dove","value":800,"daily_double":false,"type":"text"},{"clue":"A stroke to express affection","answer":"Caress","value":1200,"daily_double":false,"type":"text"},{"clue":"A type of dentin","answer":"Ivory","value":1600,"daily_double":false,"type":"text"},{"clue":"The outer part of an orange peel","answer":"Zest","value":2000,"daily_double":false,"type":"text"}]},{"name":"U.S. ISLANDS","questions":[{"clue":"It's New York City's smallest borough in population","answer":"Staten Island","value":400,"daily_double":false,"type":"text"},{"clue":"Now a resort, Put-In-Bay on Ohio's South Bass Island in this lake was a naval base for Oliver Hazard Perry","answer":"Erie","value":800,"daily_double":false,"type":"text"},{"clue":"To remember the islands in this R.I. bay, \"Prudence, Patience, Hope & Despair; & Little Hog Island right over there\"","answer":"Narragansett","value":1200,"daily_double":false,"type":"text"},{"clue":"3 islands lie within this lake in New York's Adirondacks; Buck Island, Moose Island & Hawk Island","answer":"Lake Placid","value":1600,"daily_double":true,"type":"text"},{"clue":"This island off Georgia was named for a friend of James Robert Oglethorpe, not a Robert Louis Stevenson doctor","answer":"Jekyll","value":2000,"daily_double":false,"type":"text"}]},{"name":"BEFORE & AFTER AT THE MOVIES","questions":[{"clue":"A \"Norma Rae\" Oscar winner heads into the corn to play baseball with Kevin Costner & Shoeless Joe","answer":"Sally Field of Dreams","value":400,"daily_double":false,"type":"text"},{"clue":"Tom Hanks & his soldiers storm the beaches of Normandy & rescue the guy who played Oliver in \"Love Story\"","answer":"Saving Private Ryan O'Neal","value":800,"daily_double":false,"type":"text"},{"clue":"The prince's kiss awakens her with a \"Grease\" song that says, \"No graduation day for you... flunked shampoo\"","answer":"Sleeping Beauty-School Dropout","value":1200,"daily_double":false,"type":"text"},{"clue":"The Edsels' 1961 doo-wop hit is a song by Dorothy & the Munchkins celebrating a notable demise in \"The Wizard of Oz\"","answer":"Rama Lama Ding-Dong! The Wicked Witch Is Dead","value":1600,"daily_double":false,"type":"text"},{"clue":"The film for which Sandra Bullock won an Oscar is an unintended consequence of taking a medication","answer":"The Blind Side Effect","value":2000,"daily_double":false,"type":"text"}]}],"final":{"category":"GROUNDBREAKING NONFICTION","clue":"Chapters in this 1962 classic include \"Earth's Green Mantle\", \"Needless Havoc\", \"Rivers of Death\" & \"And No Birds Sing\"","answer":"Silent Spring"}}