{"contestants":[{"name":"Player1","score":0},{"name":"Player2","score":0},{"name":"Player3","score":0}],"categories":[{"name":"PITCHERS","questions":[{"clue":"Feat performed May 17, 1998 by David Wells; it was only the 13th time in the 20th century","answer":"pitching a perfect game","value":200,"daily_double":false,"type":"text"},{"clue":"This strikeout king's last season, 1993, was marred by injuries & a fistfight with Robin Ventura","answer":"Nolan Ryan","value":400,"daily_double":false,"type":"text"},{"clue":"[IMAGE CLUE]<br \/>Intimidating moundsman seen here","answer":"Randy Johnson","value":600,"daily_double":false,"type":"text"},{"clue":"Inducted into the Hall of Fame in 1971, he got his nickname carrying bags at a Mobile, Alabama depot","answer":"Leroy \"Satchel\" Paige","value":1600,"daily_double":true,"type":"text"},{"clue":"This pitcher named for a U.S. president was played by Ronald Reagan in \"The Winning Team\"","answer":"Grover Cleveland Alexander","value":1000,"daily_double":false,"type":"text"}]},{"name":"THE CIVIL WAR","questions":[{"clue":"A century before the U.S.S. Nautilus, the Confederacy had 2 of these new ships, the Pioneer  & the Hunley","answer":"submarines","value":200,"daily_double":false,"type":"text"},{"clue":"This July 1861 campaign in Virginia began as the Affair at Blackburn's Ford","answer":"First Bull Run","value":400,"daily_double":false,"type":"text"},{"clue":"This grandson of the ninth president commanded troops in the Army of the Cumberland","answer":"Benjamin Harrison","value":600,"daily_double":false,"type":"text"},{"clue":null,"answer":null,"value":null,"daily_double":false},{"clue":null,"answer":null,"value":null,"daily_double":false}]},{"name":"KIDDIE LIT","questions":[{"clue":"This Rudyard Kipling classic begins with the story of \"Mowgli's Brothers\"","answer":"The Jungle Book","value":200,"daily_double":false,"type":"text"},{"clue":"She's Jane & Michael Banks' magical nanny","answer":"Mary Poppins","value":400,"daily_double":false,"type":"text"},{"clue":"A famous book by Crockett Johnson tells of a little boy named Harold & his adventures with this color crayon","answer":"purple","value":600,"daily_double":false,"type":"text"},{"clue":"It's no secret, \"The Long Secret\" was Louise Fitzhugh's sequel to this book about a little girl snoop","answer":"Harriet the Spy","value":800,"daily_double":false,"type":"text"},{"clue":"The 1986 Newbery Medal went to this book about a mail-order bride who joins a family on the prairie","answer":"Sarah, Plain and Tall","value":1000,"daily_double":false,"type":"text"}]},{"name":"IN THE DICTIONARY","questions":[{"clue":"The snipe in guttersnipe is one of these creatures that frequent the mud at the edge of a pond","answer":"a bird","value":200,"daily_double":false,"type":"text"},{"clue":"Meaning to vacillate between 2 choices, this phrase was originally \"shall I, shall I\"","answer":"shilly-shally","value":400,"daily_double":false,"type":"text"},{"clue":"From the French for \"discomfited\", to be \"left in\" this is to be left in trouble without help","answer":"the lurch","value":600,"daily_double":false,"type":"text"},{"clue":"This 3-letter word for \"class\" or \"kind\" usually follows the phrase \"of that...\"","answer":"ilk","value":800,"daily_double":false,"type":"text"},{"clue":"This word meaning \"to gad about\" may be an alteration of gallant","answer":"gallivant","value":1000,"daily_double":false,"type":"text"}]},{"name":"COURAGEOUS CAPTAINS","questions":[{"clue":"He finally won an Oscar in 1952 for playing a raffish yet courageous riverboat captain","answer":"Humphrey Bogart (The African Queen)","value":200,"daily_double":false,"type":"text"},{"clue":"In a Herman Wouk novel, crazy Captain Queeg commanded this vessel","answer":"Caine","value":400,"daily_double":false,"type":"text"},{"clue":"The British captured this courageous captain Sept. 21, 1776 on his return from a spy mission","answer":"Nathan Hale","value":600,"daily_double":false,"type":"text"},{"clue":"Killed by Communist forces 10 days after WWII, this U.S. Army captain has his own \"Society\"","answer":"John Birch","value":1600,"daily_double":true,"type":"text"},{"clue":"The courageous captain of this spectral ship is condemned to sail the seas until judgment day","answer":"the Flying Dutchman","value":1000,"daily_double":false,"type":"text"}]},{"name":"POUR ME SOME CHAMPAGNE!","questions":[{"clue":"A little red wine is usually added to make this popular color of champagne","answer":"ros\u00e9 (or pink)","value":200,"daily_double":false,"type":"text"},{"clue":"A classic champagne cocktail contains a dash of the Angostura type of this ingredient","answer":"bitters","value":400,"daily_double":false,"type":"text"},{"clue":"The songwriter who wrote, \"I get no kick from champagne, mere alcohol doesn't thrill me at all\"","answer":"Cole Porter","value":600,"daily_double":false,"type":"text"},{"clue":null,"answer":null,"value":null,"daily_double":false},{"clue":null,"answer":null,"value":null,"daily_double":false}]}],"final":{"category":"U.S. ORGANIZATIONS","clue":"A New Deal agency & a present-day organization, both using an eagle symbol, share these initials","answer":"NRA (National Recovery Administration & National Rifle Association)"}}