{"contestants":[{"name":"Player1","score":0},{"name":"Player2","score":0},{"name":"Player3","score":0}],"categories":[{"name":"LAKERS","questions":[{"clue":"Locals in this Upstate New York City know it hosted the 1980 winter Olympics","answer":"Lake Placid","value":200,"daily_double":false,"type":"text"},{"clue":"[IMAGE CLUE]<br \/>Folks on the Nevada border know this lake took its name from the Washoe word for \"Big Water\"","answer":"Lake Tahoe","value":400,"daily_double":false,"type":"text"},{"clue":"Workers are way above average in ports such as Duluth on this Great Lake","answer":"Lake Superior","value":600,"daily_double":false,"type":"text"},{"clue":"People walk like Egyptians around this lake formed by the creation of the Aswan High Dam","answer":"Lake Nasser","value":800,"daily_double":false,"type":"text"},{"clue":"U.N. office workers in Switzerland overlook this lake & have a view of the Alps","answer":"Lake Geneva","value":1000,"daily_double":false,"type":"text"}]},{"name":"THEIR MAIN MUSICAL INSTRUMENT","questions":[{"clue":"Billy Joel","answer":"the piano","value":200,"daily_double":false,"type":"text"},{"clue":"Kenny G","answer":"the saxophone","value":400,"daily_double":false,"type":"text"},{"clue":"Yo-Yo Ma","answer":"the cello","value":600,"daily_double":false,"type":"text"},{"clue":"Woody Allen","answer":"the clarinet","value":800,"daily_double":false,"type":"text"},{"clue":"Steven Van Zandt","answer":"the guitar","value":1000,"daily_double":false,"type":"text"}]},{"name":"SQUAWK ON THE STREET","questions":[{"clue":"Genus Otus includes the screech type of this nocturnal bird","answer":"an owl","value":200,"daily_double":false,"type":"text"},{"clue":"The scarlet macaw, part of this talkative family, has beautiful plumage but an ugly squawk","answer":"parrots","value":400,"daily_double":false,"type":"text"},{"clue":"[IMAGE CLUE]<br \/>It's a bird, it's a crane, & it's named for its call","answer":"a whooping (crane)","value":600,"daily_double":false,"type":"text"},{"clue":null,"answer":null,"value":null,"daily_double":false},{"clue":null,"answer":null,"value":null,"daily_double":false}]},{"name":"FINE FOOD","questions":[{"clue":null,"answer":null,"value":null,"daily_double":false},{"clue":null,"answer":null,"value":null,"daily_double":false},{"clue":null,"answer":null,"value":null,"daily_double":false},{"clue":null,"answer":null,"value":null,"daily_double":false},{"clue":null,"answer":null,"value":null,"daily_double":false}]},{"name":"THE FIVE","questions":[{"clue":"The 5 movie ratings in the U.S. are NC-17, R, PG, PG-13 & this one","answer":"G","value":200,"daily_double":false,"type":"text"},{"clue":"Including first, in which the heels are together, there are 5 basic foot positions in the classical type of this","answer":"ballet","value":400,"daily_double":false,"type":"text"},{"clue":"Dolly Parton wrote, \"Workin\"' these hours, \"what a way to make a livin\"'","answer":"9 to 5","value":600,"daily_double":false,"type":"text"},{"clue":"\"The Five Ways\", a work of 13th c. philosophy, lays out 5 proofs for the existence of this being","answer":"God","value":800,"daily_double":false,"type":"text"},{"clue":"Irene Hunt's novel \"Across Five Aprils\" takes place over the long years of this American conflict","answer":"the Civil War","value":1000,"daily_double":false,"type":"text"}]},{"name":"THE NEW YORK TIMES 21st CENTURY HEADLINES","questions":[{"clue":"In 2003 the headline read, \"Davis Is Out, Schwarzenegger Is In by Big Margins in California\" in this type of vote","answer":"a recall","value":200,"daily_double":false,"type":"text"},{"clue":"Howard Stern made the front page in 2004 after his \"Rich Deal in Jump to\" this type of radio","answer":"satellite radio","value":400,"daily_double":false,"type":"text"},{"clue":null,"answer":null,"value":null,"daily_double":false},{"clue":null,"answer":null,"value":null,"daily_double":false},{"clue":null,"answer":null,"value":null,"daily_double":false}]}],"final":{"category":"MUSEUMS","clue":"Completed in 1959, it's been variously described as a snail, a concrete tornado, even a giant wedding cake","answer":"the Guggenheim Museum"}}