{"contestants":[{"name":"Player1","score":0},{"name":"Player2","score":0},{"name":"Player3","score":0}],"categories":[{"name":"TRAVEL & TOURISM","questions":[{"clue":"Visiting the New York Transit Exhibit in Brooklyn, you can pay the admission fee with 1 of these","answer":"a subway token","value":200,"daily_double":false,"type":"text"},{"clue":"The Boston Tea Party Ship & Museum allows visitors to engage in this unique activity","answer":"throw tea overboard","value":400,"daily_double":false,"type":"text"},{"clue":"This city's World's Fair, held in 1967, is perpetuated each summer under title \"Man & His World\"","answer":"Montreal","value":600,"daily_double":false,"type":"text"},{"clue":"Located 3 miles outside town, it's Hodgenville, Kentucky's most famous tourist attraction","answer":"Lincoln's birthplace","value":800,"daily_double":false,"type":"text"},{"clue":"You can visit the infamous Andersonville Civil War Prison, a National Historic Site, in this state","answer":"Georgia","value":1000,"daily_double":false,"type":"text"}]},{"name":"TWAIN","questions":[{"clue":"Twain said \"the art\" of frying this fowl \"cannot be learned north of the line of Mason & Dixon\"","answer":"chicken","value":200,"daily_double":false,"type":"text"},{"clue":"Character who refers to \"The Adventures of Tom Sawyer\" in the 1st line of his book","answer":"Huckleberry Finn","value":400,"daily_double":false,"type":"text"},{"clue":"On their 1st \"date\" Twain took his future wife to a reading given by this English author in 1867","answer":"Charles Dickens","value":600,"daily_double":false,"type":"text"},{"clue":"His actual middle name","answer":"Langhorne","value":800,"daily_double":false,"type":"text"},{"clue":"According to the title, it's what Twain was \"Following\" in his last travel book","answer":"the equator","value":1000,"daily_double":false,"type":"text"}]},{"name":"THE TROJAN WAR","questions":[{"clue":"In the \"Illiad\" he's described as a huge, slow-witted warrior, not a foaming cleanser","answer":"Ajax","value":200,"daily_double":false,"type":"text"},{"clue":"Menelaus, husband of Helen, was king of this city, later the historic rival of Athens","answer":"Sparta","value":400,"daily_double":false,"type":"text"},{"clue":"Some say it was this wandering warrior from Ithaca who suggested the Trojan Horse","answer":"Odysseus","value":600,"daily_double":false,"type":"text"},{"clue":"He killed Hector, then Paris killed him","answer":"Achilles","value":800,"daily_double":false,"type":"text"},{"clue":"Virgil says this man escaped the fall of Troy along with a few followers & later founded Rome","answer":"Aeneas","value":1000,"daily_double":false,"type":"text"}]},{"name":"TAXES","questions":[{"clue":"It was in 1943 that the federal government began having this done to workers' paychecks","answer":"withholding","value":200,"daily_double":false,"type":"text"},{"clue":"The IRS estimates that for fiscal 1987, this will happen to 1 of every 68 tax returns","answer":"auditing","value":400,"daily_double":false,"type":"text"},{"clue":"At 7 1\/2%, Connecticut has the highest statewide tax of this kind","answer":"sales tax","value":600,"daily_double":false,"type":"text"},{"clue":"The Tax Foundation says that in 1930 it was February 13, but in 1987 it was May 4","answer":"Tax Freedom Day","value":1600,"daily_double":true,"type":"text"},{"clue":"Chief Justice John Marshall said, \"The power to tax involves the power to\" do this","answer":"to destroy","value":1000,"daily_double":false,"type":"text"}]},{"name":"TEXAS","questions":[{"clue":"When the United States became a nation in 1776, Texas was ruled by this country","answer":"Spain","value":200,"daily_double":false,"type":"text"},{"clue":"It's said the line between the East & the West lies between these 2 large neighboring cities","answer":"Dallas & Fort Worth","value":400,"daily_double":false,"type":"text"},{"clue":"Largest lake entirely in Texas is named for this long-time Speaker of the House","answer":"Sam Rayburn","value":600,"daily_double":false,"type":"text"},{"clue":"Each year from 1932-86, up to 100,000 attended this annual event sponsored by the Texas Dept. of Corrections","answer":"the Texas Prison Rodeo","value":800,"daily_double":false,"type":"text"},{"clue":"A national seashore covers much of this 100-mile-long island named for Fr. Nicolas Balli, a Spanish priest","answer":"Padre Island","value":1000,"daily_double":false,"type":"text"}]},{"name":"TOUGH DISNEY","questions":[{"clue":"Both Disneyland & Walt Disney World's Magic Kingdom are located in counties with this name","answer":"Orange County","value":200,"daily_double":false,"type":"text"},{"clue":"Technical reason the 3rd Mickey Mouse cartoon \"Steamboat Willie\" was released 1st, on Nov. 18, 1928","answer":"because it had sound","value":800,"daily_double":true,"type":"text"},{"clue":"For \"Pinocchio\", he was painted with 27 colors; for \"Mickey Mouse Club\", they used only 9","answer":"Jiminy Cricket","value":600,"daily_double":false,"type":"text"},{"clue":"According to the 1953 cartoon, these four sounds are \"where the music comes from\"","answer":"a toot, a whistle, a plunk & a boom","value":800,"daily_double":false,"type":"text"},{"clue":"Title character of this 1961 live-action hit was named Ned Brainard","answer":"The Absent-Minded Professor","value":1000,"daily_double":false,"type":"text"}]}],"final":{"category":"THE CABINET","clue":"1 of 2 Cabinet dept. heads who have held their position for the entire Reagan administration thus far","answer":"Caspar Weinberger (Secretary of Defense) or Samuel Pierce of HUD"}}