{"contestants":[{"name":"Player1","score":0},{"name":"Player2","score":0},{"name":"Player3","score":0}],"categories":[{"name":"AVIATION","questions":[{"clue":"Airline that the koala says it hates","answer":"Qantas","value":100,"daily_double":false,"type":"text"},{"clue":"Though they have no engine & are heavier than air, they can fly in air currents","answer":"gliders","value":200,"daily_double":false,"type":"text"},{"clue":"It's the only SST currently operating commercially in USA","answer":"the Concorde","value":300,"daily_double":false,"type":"text"},{"clue":null,"answer":null,"value":null,"daily_double":false},{"clue":null,"answer":null,"value":null,"daily_double":false}]},{"name":"MOVIE MONSTERS","questions":[{"clue":"In the '76 remake, he fell from the World Trade Center","answer":"King Kong","value":100,"daily_double":false,"type":"text"},{"clue":"In Japan, he's known as \"Gojira\"","answer":"Godzilla","value":200,"daily_double":false,"type":"text"},{"clue":"Affliction that made monsters of Grant Williams in '57 & Lily Tomlin in '81","answer":"shrinking","value":300,"daily_double":false,"type":"text"},{"clue":"Bram Stoker popularized this monster, the one most often portrayed in movies","answer":"(Count) Dracula","value":400,"daily_double":false,"type":"text"},{"clue":"They were \"Them!\"","answer":"ants","value":500,"daily_double":false,"type":"text"}]},{"name":"STARTS WITH \"M\"","questions":[{"clue":"Daniel Boone's Cherokee chum played by Ed Ames","answer":"Mingo","value":100,"daily_double":false,"type":"text"},{"clue":"Planet Flash Gordon saved the Earth from","answer":"Mongo","value":200,"daily_double":false,"type":"text"},{"clue":"Native to India, this tree of the sumac family is prized for its fruit","answer":"mango","value":300,"daily_double":false,"type":"text"},{"clue":"[IMAGE CLUE]<br \/>Goes with \"Jerrie\" for a T.S. Eliot cat or \"Jerry\" for singers of following\"In the summer time when the weather is high \/ You can stretch right up and touch the sky \/ When the weather's fine\"","answer":"Mungo","value":800,"daily_double":true,"type":"text"},{"clue":null,"answer":null,"value":null,"daily_double":false}]},{"name":"NOTABLE ANIMALS","questions":[{"clue":"Siam, 1st of this cat breed in the U.S., was a gift to Pres. Rutherford B. Hayes in 1878","answer":"Siamese (cats)","value":100,"daily_double":false,"type":"text"},{"clue":"Buddy, the 1st dog trained as this, came to the U.S. in 1928","answer":"a seeing-eye dog","value":200,"daily_double":false,"type":"text"},{"clue":"In 1961, Enos, a chimp became the 1st to do this for the U.S.","answer":"orbit the Earth","value":300,"daily_double":false,"type":"text"},{"clue":"In 1947, \"Islero\", a fierce bull, killed & was killed by him, perhaps the world's greatest bullfighter","answer":"Manolete","value":400,"daily_double":false,"type":"text"},{"clue":null,"answer":null,"value":null,"daily_double":false}]},{"name":"STATE CAPITALS","questions":[{"clue":"Under Russian rule, Sitka was its capital","answer":"Alaska","value":100,"daily_double":false,"type":"text"},{"clue":"Originally called \"Waterloo\", it's the capital of Texas","answer":"Austin","value":200,"daily_double":false,"type":"text"},{"clue":null,"answer":null,"value":null,"daily_double":false},{"clue":null,"answer":null,"value":null,"daily_double":false},{"clue":null,"answer":null,"value":null,"daily_double":false}]},{"name":"TV NUMBERS","questions":[{"clue":"Edd \"Kookie\" Byrnes' \"working address\"","answer":"77 Sunset Strip","value":100,"daily_double":false,"type":"text"},{"clue":"In '60s sitcom, officers Toody & Muldoon patrolled the Bronx in this vehicle","answer":"Car 54","value":200,"daily_double":false,"type":"text"},{"clue":"Number of lives led by Richard Carlson while portraying Herbert Philbrick","answer":"three","value":300,"daily_double":false,"type":"text"},{"clue":"Each day, Art Linkletter interviewed this many children on his \"House Party\" show","answer":"four","value":400,"daily_double":false,"type":"text"},{"clue":"Number of Sgt. Friday's badge, under which name \"Dragnet\" went into reruns","answer":"714","value":500,"daily_double":false,"type":"text"}]}],"final":{"category":"GAMES","clue":"The 1 word most frequently found in the center square of a bingo card","answer":"Free"}}