{"contestants":[{"name":"Player1","score":0},{"name":"Player2","score":0},{"name":"Player3","score":0}],"categories":[{"name":"SEVEN DEADLY SYNONYMS","questions":[{"clue":"Type of error that causes a program to abort, or of attraction that caused Michael Douglas to notice Glenn Close","answer":"fatal","value":400,"daily_double":false,"type":"text"},{"clue":"Often found before \"maniac\", this word refers to a murderer","answer":"homicidal","value":800,"daily_double":false,"type":"text"},{"clue":"A substance that tends to cause cancer is deemed this 12-letter word","answer":"carcinogenic","value":1200,"daily_double":false,"type":"text"},{"clue":"This type of wound that kills you comes from the Latin for \"death\"","answer":"mortal","value":1600,"daily_double":false,"type":"text"},{"clue":"This adjective from the word \"virus\" can describe a deadly strain of a disease","answer":"virulent","value":2000,"daily_double":false,"type":"text"}]},{"name":"WORLD CAPITALS","questions":[{"clue":"If you really, really want to visit North Korea, you'll probably fly into this city's Sunan Intl. Airport","answer":"Pyongyang","value":400,"daily_double":false,"type":"text"},{"clue":"In 1749 the French laid out this Caribbean capital in a grid pattern & called it L'Hopital","answer":"Port-au-Prince","value":800,"daily_double":false,"type":"text"},{"clue":"It's continental Europe's westernmost national capital","answer":"Lisbon","value":1200,"daily_double":true,"type":"text"},{"clue":"This South American capital is the only city planned & built in the 20th century to be made a World Heritage site","answer":"Brasilia","value":1600,"daily_double":false,"type":"text"},{"clue":"Thimphu, capital of this Himalayan kingdom, is said to be the only world capital without traffic lights","answer":"Bhutan","value":2000,"daily_double":false,"type":"text"}]},{"name":"THE ARTS","questions":[{"clue":"The name of this leading ballet company means \"great ballet\" in Russian","answer":"Bolshoi","value":400,"daily_double":false,"type":"text"},{"clue":"[IMAGE CLUE]<br \/>Here is Eugene Delacroix's depiction of the death of this Shakespeare character","answer":"Ophelia","value":800,"daily_double":true,"type":"text"},{"clue":"Erato, the muse of love poetry, is depicted holding this harp-like instrument","answer":"a lyre","value":1200,"daily_double":false,"type":"text"},{"clue":"[IMAGE CLUE]<br \/>Here's a poster by Czech artist Alphonse Mucha in this style that flourished from about 1880 to 1910","answer":"Art Nouveau","value":1600,"daily_double":false,"type":"text"},{"clue":"Denzel Washington \"arrived\" on Broadway as Hickey in a 2018 revival of this drama by Eugene O'Neill","answer":"The Iceman Cometh","value":2000,"daily_double":false,"type":"text"}]},{"name":"THINGS ARE GETTING BETTER","questions":[{"clue":"Medical miracles march on: guinea worm, which in 1985 had 3 million cases on this continent, is on the verge of eradication","answer":"Africa","value":400,"daily_double":false,"type":"text"},{"clue":"A bestseller by Steven Pinker about the joys of progress is called this 18th century era of reason \"Now\"","answer":"Enlightenment","value":800,"daily_double":false,"type":"text"},{"clue":"As Dr. King put it, \"The arc of the moral universe is long, but it bends toward\" this quality","answer":"justice","value":1200,"daily_double":false,"type":"text"},{"clue":"The 1964 exhibit \"Progressland\" was sponsored by this giant power-&-more company","answer":"General Electric","value":1600,"daily_double":false,"type":"text"},{"clue":"In the 1933 utopian work \"Life in\" this kind of -ocracy run by scientists, every citizen gets a yearly energy allotment in ergs","answer":"technocracy","value":2000,"daily_double":false,"type":"text"}]},{"name":"A POP \"UP\" CATEGORY","questions":[{"clue":"A song by the late Avicii says, \"So\" do this \"when it's all over, whem I'm wiser and I'm older\"","answer":"wake me up","value":400,"daily_double":false,"type":"text"},{"clue":"Joe Cocker & Jennifer Warnes took this love theme from \"An Officer and a Gentleman\" to No. 1","answer":"\"Up Where We Belong\"","value":800,"daily_double":false,"type":"text"},{"clue":"Andra Day said this inspirational song started as \"sort of a prayer\" after a friend was diagnosed with cancer","answer":"\"Rise Up\"","value":1200,"daily_double":false,"type":"text"},{"clue":"In 2018 Drake rapped about feeling this, \"Hundred thousand on my head, it's disrespect\"","answer":"\"Upset\"","value":1600,"daily_double":false,"type":"text"},{"clue":"\"And if this old world starts getting you down, there's room enough for two\" here","answer":"\"Up On The Roof\"","value":2000,"daily_double":false,"type":"text"}]},{"name":"HODGEPODGE","questions":[{"clue":"This automaker automakes the Focus ST","answer":"Ford","value":400,"daily_double":false,"type":"text"},{"clue":"It's the largest U.S. state in area that borders the Pacific Ocean","answer":"Alaska","value":800,"daily_double":false,"type":"text"},{"clue":"It's the number of strings on a standard guitar","answer":"six","value":1200,"daily_double":false,"type":"text"},{"clue":"It's the heat needed to raise the temperature of a gram of water one degree Celsius","answer":"a calorie","value":1600,"daily_double":false,"type":"text"},{"clue":"This is a blank page at the beginning or end of a book, not a spot for bugs to gather on a plant","answer":"a flyleaf","value":2000,"daily_double":false,"type":"text"}]}],"final":{"category":"SCI-FI TV","clue":"One of the twin planets this alien race called home was Remus","answer":"the Romulans"}}