{"contestants":[{"name":"Player1","score":0},{"name":"Player2","score":0},{"name":"Player3","score":0}],"categories":[{"name":"THE OLD WEST","questions":[{"clue":"The Book of the American West says most of these pack animals seem to come from Missouri","answer":"mules","value":200,"daily_double":false,"type":"text"},{"clue":"The Sharps rifles preacher Henry Ward Beecher sent to Kansas settlers were nicknamed this","answer":"Beecher's Bibles","value":400,"daily_double":false,"type":"text"},{"clue":"In 1858 Lt. Joseph Ives led the 1st party 1 mile down to the bottom of this","answer":"the Grand Canyon","value":600,"daily_double":false,"type":"text"},{"clue":"With a band playing \"Garryowen\" he led the 7th Cavalry against Black Kettle in 1868","answer":"George Armstrong Custer","value":800,"daily_double":false,"type":"text"},{"clue":"Nevada town that was the business center for the Comstock Mine","answer":"Virginia City","value":1000,"daily_double":false,"type":"text"}]},{"name":"THE MIDDLE EAST","questions":[{"clue":"In 1973 this Hashemite kingdom finally gave women the right to vote","answer":"Jordan","value":200,"daily_double":false,"type":"text"},{"clue":"The Gulf of Oman is connected with the Persian Gulf by this strategic strait","answer":"the Strait of Hormuz","value":400,"daily_double":false,"type":"text"},{"clue":"Tabriz is the largest city in this country's part of Azerbaijan","answer":"Iran","value":600,"daily_double":false,"type":"text"},{"clue":"When this Saudi king was assassinated by a nephew in March 1975 he was succeeded by his brother Khalid","answer":"King Faisal","value":1600,"daily_double":true,"type":"text"},{"clue":"The Beqaa Valley is this small country's main agricultural region","answer":"Lebanon","value":1000,"daily_double":false,"type":"text"}]},{"name":"MYTHOLOGY","questions":[{"clue":"In Norse mythology Fenrir is a huge one these lupine animals","answer":"a wolf","value":200,"daily_double":false,"type":"text"},{"clue":"We assume that Themis, a consort of Zeus, was destined to the mother of this trio","answer":"the Fates","value":400,"daily_double":false,"type":"text"},{"clue":"Greek goddess of wisdom who invented the flute but didn't like the way it puffed out her cheeks","answer":"Athena","value":600,"daily_double":false,"type":"text"},{"clue":"It was the name of the Acadian goddess of fertility engaging ancient Babylon & a 1987 film flop","answer":"Ishtar","value":800,"daily_double":false,"type":"text"},{"clue":"For a time Creon thought that both Ismene & this sister were guilty of burying Polynices","answer":"Antigone","value":1000,"daily_double":false,"type":"text"}]},{"name":"NEW JERSEYIANS","questions":[{"clue":"Born in what's now Trenton, this explorer never reached the top of the Colorado peak that bears his name","answer":"Pike","value":200,"daily_double":false,"type":"text"},{"clue":"His large estate in Hopewell was the site of the famous 1932 kidnapping","answer":"Charles Lindbergh","value":400,"daily_double":false,"type":"text"},{"clue":"This senator spent two years at Oxford on a Rhodes Scholarship before playing for the N.Y. Knicks","answer":"Bill Bradley","value":600,"daily_double":false,"type":"text"},{"clue":"This scientist lived at 112 Mercer St. in Princeton from 1935 until his death in 1955","answer":"Albert Einstein","value":800,"daily_double":false,"type":"text"},{"clue":"This poet died at 330 Mickle St. in Camden in 1892","answer":"Walt Whitman","value":1000,"daily_double":false,"type":"text"}]},{"name":"ARCHITECTS","questions":[{"clue":"Thomas Walter designed an iron dome to replace this D.C. building's original one","answer":"the Capitol","value":200,"daily_double":false,"type":"text"},{"clue":"Buckminster Fuller designed this type of dome for the U.S. Pavilion at Expo 67","answer":"a geodesic dome","value":400,"daily_double":false,"type":"text"},{"clue":"This Doric temple on the Acropolis was built by Ictinus & Callicrates","answer":"the Parthenon","value":600,"daily_double":false,"type":"text"},{"clue":"Ludwig Mies appended this, his mother's surname, to his own","answer":"van der Rohe","value":800,"daily_double":false,"type":"text"},{"clue":"\"Inside the Third Reich\" is a memoir by this man, Hitler's chief architect","answer":"Albert Speer","value":1000,"daily_double":false,"type":"text"}]},{"name":"2-CHARACTER PLAYS","questions":[{"clue":"Alan Alda personified this title bird captured by a pussycat in the 1964 Broadway hit","answer":"The Owl and the Pussycat","value":200,"daily_double":false,"type":"text"},{"clue":"Anne Bancroft won a Tony for her Broadway debut as 1 of the \"Two for\" this playground toy","answer":"a seesaw","value":400,"daily_double":false,"type":"text"},{"clue":"In Willy Russell's play Frank is an English tutor who tried educating this hairdresser","answer":"Miss Rita","value":600,"daily_double":false,"type":"text"},{"clue":"The entire action of this 1951 play takes place in a bedroom & much of it on the title bed","answer":"The Fourposter","value":1600,"daily_double":true,"type":"text"},{"clue":"Hume Cronyn & Jessica Tandy got to know each other over the title pastime in this 1977 play","answer":"The Gin Game","value":1000,"daily_double":false,"type":"text"}]}],"final":{"category":"VICE PRESIDENTS","clue":"He was the last vice president who didn't serve a full 4-year term","answer":"Nelson Rockefeller"}}