{"contestants":[{"name":"Player1","score":0},{"name":"Player2","score":0},{"name":"Player3","score":0}],"categories":[{"name":"U.S. HISTORY","questions":[{"clue":"In 1903, the U.S. & U.K. settled their old dispute over the boundary between Canada & this U.S. territory","answer":"Alaska","value":200,"daily_double":false,"type":"text"},{"clue":"It was the colonial capital of Virginia in 1700 & when you visit it today, you'll swear it still is","answer":"Williamsburg","value":400,"daily_double":false,"type":"text"},{"clue":"This was finally ratified 3\/4 of the states & went into force in December 1791","answer":"the Bill of Rights","value":600,"daily_double":false,"type":"text"},{"clue":"Though the 4th, not the 1st, chief justice, he did more than any other to shape the Supreme Court","answer":"John Marshall","value":800,"daily_double":false,"type":"text"},{"clue":"Usually known by name of a Maryland creek, this 1862 battle is known as the bloodiest day of the Civil War","answer":"Antietam","value":1000,"daily_double":false,"type":"text"}]},{"name":"9-LETTER WORDS","questions":[{"clue":"[IMAGE CLUE]<br \/>9-letter word found in the title of the following:\"Spider Murphy played the tenor saxophone \/Little Joe was blowin' on the slide trombone \/The drummer boy from Illinois went crash, boom, bang...\"","answer":"jailhouse (\"Jailhouse Rock\" by Elvis Presley)","value":400,"daily_double":true,"type":"text"},{"clue":"Traditionally, hay fever sufferers have blamed this for their misery, but ragweed is the real culprit","answer":"goldenrod","value":400,"daily_double":false,"type":"text"},{"clue":null,"answer":null,"value":null,"daily_double":false},{"clue":null,"answer":null,"value":null,"daily_double":false},{"clue":null,"answer":null,"value":null,"daily_double":false}]},{"name":"SHIPS","questions":[{"clue":"In October 1987, in the S. Pacific, one of these erupted 130' beneath the research ship Melville","answer":"a volcano","value":200,"daily_double":false,"type":"text"},{"clue":"In Sept. 1987 the Walt Disney Company announced plans to buy this Calif. tourist attraction","answer":"the Queen Mary","value":400,"daily_double":false,"type":"text"},{"clue":"For clipper ships, this attribute was the top priority","answer":"speed","value":600,"daily_double":false,"type":"text"},{"clue":"Mississippi riverboat named for the outlet of the Sacramento River, where it originally ran","answer":"the Delta Queen","value":800,"daily_double":false,"type":"text"},{"clue":"The 1st nuclear submarine was produced in this state's shipyards","answer":"Connecticut","value":1000,"daily_double":false,"type":"text"}]},{"name":"WOMEN IN FICTION","questions":[{"clue":"Both Rebecca & Rowena love this title hero of a Sir Walter Scott romance","answer":"(Wilfred of) Ivanhoe","value":200,"daily_double":false,"type":"text"},{"clue":"Esmeralda, a lovely gypsy accused of witchcraft, finds a genuine protector in him","answer":"The Hunchback of Notre-Dame","value":400,"daily_double":false,"type":"text"},{"clue":"The nickname of Annie P. Miller, heroine of a Henry James novella","answer":"Daisy Miller","value":600,"daily_double":false,"type":"text"},{"clue":"She was the object of Heathcliff's obsessive desire","answer":"Cathy (Earnshaw)","value":800,"daily_double":false,"type":"text"},{"clue":"Supposedly, Tolstoy got the idea for this book after seeing a woman who had jumped in front of a train","answer":"Anna Karenina","value":1000,"daily_double":false,"type":"text"}]},{"name":"THE MOUNTIES","questions":[{"clue":"Mounties must have a Canadian driver's license & no criminal record, & speak either of these 2 languages","answer":"English & French","value":200,"daily_double":false,"type":"text"},{"clue":"These people have been recruited as Mounties only since 1974","answer":"women","value":400,"daily_double":false,"type":"text"},{"clue":"The Mounties are the only police force in these 2 Canadian territories","answer":"the Yukon Territory & the Northwest Territories","value":600,"daily_double":false,"type":"text"},{"clue":"The Mounties weren't \"Royal\" until 1904, by this monarch's decree","answer":"Edward VII","value":800,"daily_double":false,"type":"text"},{"clue":"Besides Quebec, the only Canadian province not policed by the Mounties","answer":"Ontario","value":2000,"daily_double":true,"type":"text"}]},{"name":"GOING FOR BAROQUE","questions":[{"clue":"Antonio Vivaldi dies in poverty & obscurity in this Austrian city, not his native Venice","answer":"Vienna","value":200,"daily_double":false,"type":"text"},{"clue":"Like many notable Baroque composers, Couperin held this instrumental post in a church","answer":"organist","value":400,"daily_double":false,"type":"text"},{"clue":"Most authorities recognize the beginning of this century as the start of the Baroque period","answer":"the 17th century","value":600,"daily_double":false,"type":"text"},{"clue":null,"answer":null,"value":null,"daily_double":false},{"clue":null,"answer":null,"value":null,"daily_double":false}]}],"final":{"category":"CENTRAL AMERICA","clue":"Some 18 years before starting Panama Canal, the U.S. began a canal in this country but abandoned it","answer":"Nicaragua"}}