{"contestants":[{"name":"Player1","score":0},{"name":"Player2","score":0},{"name":"Player3","score":0}],"categories":[{"name":"HERSTORY","questions":[{"clue":"During the Crimean War, this British nurse toured the soldiers' hospital at night with her lantern","answer":"Florence Nightingale","value":100,"daily_double":false,"type":"text"},{"clue":"She was the first of the Ptolemaic line to speak Egyptian","answer":"Cleopatra","value":200,"daily_double":false,"type":"text"},{"clue":"In 1431 a court at Rouen charged her with 70 counts, including immodesty by wearing men's clothing","answer":"Joan of Arc","value":300,"daily_double":false,"type":"text"},{"clue":"In 1975 an Allahabad court found this Indian prime minister guilty of 2 counts of corruption","answer":"Indira Gandhi","value":400,"daily_double":false,"type":"text"},{"clue":"At age 23 she was featured in Argentine radio soap operas; 4 years later she was first lady","answer":"Eva Peron","value":500,"daily_double":false,"type":"text"}]},{"name":"ACTOR-RIFIC","questions":[{"clue":"[IMAGE CLUE]<br \/>1938's \"Under Western Stars\" helped launched the career of this big-screen singing sensation:","answer":"Roy Rogers","value":100,"daily_double":false,"type":"text"},{"clue":"[IMAGE CLUE]<br \/>In Roman numerals, this actress' first name would equal 54:","answer":"Liv Tyler","value":200,"daily_double":false,"type":"text"},{"clue":"[IMAGE CLUE]<br \/>He's the 1960s Disney child actor seen here in 1979 in a different role:","answer":"Kurt Russell","value":300,"daily_double":false,"type":"text"},{"clue":"A star of 1932's \"Scarface\", this tough George once ran a Havana casino","answer":"George Raft","value":400,"daily_double":false,"type":"text"},{"clue":"[IMAGE CLUE]<br \/>(Hi, I'm Michael Boatman of Spin City.)  Early in my career I played Sam Beckett on this series about nurses that was set during the Vietnam War","answer":"China Beach","value":500,"daily_double":false,"type":"text"}]},{"name":"\"R\" TOWN","questions":[{"clue":"This Southern capital covers 63 square miles on both sides of the James River","answer":"Richmond, Virginia","value":100,"daily_double":false,"type":"text"},{"clue":"\"Believe It or Not\", Mississippi, Tennessee & West Virginia all have a town named this","answer":"Ripley","value":200,"daily_double":false,"type":"text"},{"clue":"\"Take A Ride\" through this town, named for the ancestral home of William Penn's family","answer":"Reading","value":300,"daily_double":false,"type":"text"},{"clue":"This Georgia city was founded in 1834 on a site that had 7 hills","answer":"Rome","value":400,"daily_double":false,"type":"text"},{"clue":"We wonder if Robert Goddard saw any UFOs while working on his rockets in this town","answer":"Roswell","value":500,"daily_double":false,"type":"text"}]},{"name":"ON THE MONEY","questions":[{"clue":"Seen on the notes of many countries, including Canada, she's been called \"The most prominent woman in circulation\"","answer":"Queen Elizabeth II","value":100,"daily_double":false,"type":"text"},{"clue":"Befitting his importance, this 13th century conqueror appears on Mongolia's larger currency","answer":"Genghis Khan","value":200,"daily_double":false,"type":"text"},{"clue":"Catholic leader Daniel O'Connell appears on notes of this Irish monetary unit also called a punt","answer":"Pound","value":300,"daily_double":false,"type":"text"},{"clue":"This Post-Impressionist known for his studies of Mont Sainte-Victoire is honored on French currency","answer":"Paul Cezanne","value":400,"daily_double":false,"type":"text"},{"clue":"Poet Banjo Paterson & the first lines of his \"The Man From Snowy River\" grace this country's 10-dollar note","answer":"Australia","value":500,"daily_double":false,"type":"text"}]},{"name":"LITERATURE","questions":[{"clue":"William Faulkner's novel \"Mosquitoes\" satirizes the literary life in this Louisiana city","answer":"New Orleans","value":100,"daily_double":false,"type":"text"},{"clue":"Ford Madox Ford's 4-novel series \"Parade's End\" is set during & after this war in which Ford himself was shell-shocked","answer":"World War I","value":200,"daily_double":false,"type":"text"},{"clue":"\"For men may come and men may go, but I go on forever\", this \"Lord\" of poetry babbled in \"The Brook\"","answer":"Alfred Lord Tennyson","value":300,"daily_double":false,"type":"text"},{"clue":"This 1871 sequel is subtitled \"Life at Plumfield with Jo's Boys\"","answer":"\"Little Men\"","value":800,"daily_double":true,"type":"text"},{"clue":"The title of this Willa Cather novel refers to a certain Ms. Shimerda","answer":"\"My Antonia\"","value":500,"daily_double":false,"type":"text"}]},{"name":"A PROVERBIAL MESS","questions":[{"clue":null,"answer":null,"value":null,"daily_double":false},{"clue":null,"answer":null,"value":null,"daily_double":false},{"clue":null,"answer":null,"value":null,"daily_double":false},{"clue":"At try don't you if again first try succeed","answer":"At first if you don't succeed, try, try again","value":400,"daily_double":false,"type":"text"},{"clue":"A is words picture a poem without","answer":"A picture is a poem without words","value":500,"daily_double":false,"type":"text"}]}],"final":{"category":"'90s NOTABLES","clue":"In 1999 a stretch of I-70 that runs past Busch Stadium was renamed in his honor","answer":"Mark McGwire"}}