{"contestants":[{"name":"Player1","score":0},{"name":"Player2","score":0},{"name":"Player3","score":0}],"categories":[{"name":"BUILT LIKE A GREEK GOD","questions":[{"clue":"He must have felt like hell when lots were drawn to divvy up the universe & he got the Underworld","answer":"Hades","value":400,"daily_double":false,"type":"text"},{"clue":"This means war!  Or rather, he meant war, especially when he defended his son Cycnus & took on Hercules","answer":"Ares","value":800,"daily_double":false,"type":"text"},{"clue":"He was the god of fertility, wine, vegetation & obviously, good times","answer":"Bacchus (or Dionysus)","value":1200,"daily_double":false,"type":"text"},{"clue":"This blacksmith god must have been hurt by the infidelities of his wife Aphrodite & could have said \"You're fired!\"","answer":"Hephaestus","value":1600,"daily_double":false,"type":"text"},{"clue":"[IMAGE CLUE]<br \/>Beneath the clock is this god of time--not the same as the father of Zeus, though their names sound alike","answer":"Chronos","value":2000,"daily_double":false,"type":"text"}]},{"name":"3-WORD BOOK SUMMARY","questions":[{"clue":"1895:Crane.\"Colorful\".War","answer":"The Red Badge of Courage","value":400,"daily_double":false,"type":"text"},{"clue":"1878:Vronsky.Train.Oops","answer":"Anna Karenina","value":800,"daily_double":true,"type":"text"},{"clue":"1962:Alex.Droogs.Nasty","answer":"A Clockwork Orange","value":1200,"daily_double":false,"type":"text"},{"clue":"1925:Driving.Non-Miss.Daisy","answer":"The Great Gatsby","value":1600,"daily_double":false,"type":"text"},{"clue":"1970:Canoeing--no,survival","answer":"Deliverance","value":2000,"daily_double":false,"type":"text"}]},{"name":"____ THE ____","questions":[{"clue":"19th century documents show pirates actually made victims do this, plunge to their death by stepping off a beam","answer":"walk the plank","value":400,"daily_double":false,"type":"text"},{"clue":"To do this provides little sustenance for the amount of mastication, which may be why it refers to idle chatter","answer":"chew the fat","value":800,"daily_double":true,"type":"text"},{"clue":"In 2016 this disciple of Kanye West released his \"Coloring Book\" mixtape","answer":"Chance the Rapper","value":1200,"daily_double":false,"type":"text"},{"clue":"\"Sister Carrie\" uses this dessert phrase that now means to surpass all others in a bad or unusual way","answer":"take the cake","value":1600,"daily_double":false,"type":"text"},{"clue":"The title of this \"touch and feel\" board book by Dorothy Kunhardt is a command to babies, not the name of a hare","answer":"Pat the Bunny","value":2000,"daily_double":false,"type":"text"}]},{"name":"PARDON MY FRENCH","questions":[{"clue":"At an 1802 White House dinner, Thomas Jefferson supplied the starch with these \"in the French manner\"","answer":"potatoes","value":400,"daily_double":false,"type":"text"},{"clue":"This French military group  that formed in 1831 had its first headquarters in Sidi Bel Abbes, Algeria","answer":"the French Foreign Legion","value":800,"daily_double":false,"type":"text"},{"clue":"This birthing method developed by a French doctor in the 1950s involves breath control & pain reduction","answer":"Lamaze","value":1200,"daily_double":false,"type":"text"},{"clue":"Post-WWII Juliette Greco made her mark on this style of song known simply by the French word for \"song\"","answer":"chanson","value":1600,"daily_double":false,"type":"text"},{"clue":"From the French for \"light of hand\", it's the art involved in sleight of hand","answer":"legerdemain","value":2000,"daily_double":false,"type":"text"}]},{"name":"1895","questions":[{"clue":"William G. Morgan invented this team sport that's played indoors by teams of 6 players","answer":"volleyball","value":400,"daily_double":false,"type":"text"},{"clue":"In 1895 John Holland got a Navy contract to build the Plunger, an experimental one of these","answer":"submarine","value":800,"daily_double":false,"type":"text"},{"clue":"This Asheville, North Carolina mansion was nearly finished after 6 years, so the Vanderbilts moved in","answer":"Biltmore","value":1200,"daily_double":false,"type":"text"},{"clue":"Oscar Wilde withdrew his libel case against this nobleman but the publicity led to his own conviction for \"gross indecency\"","answer":"the Marquess of Queensbury","value":1600,"daily_double":false,"type":"text"},{"clue":"These brothers showed their first movie to a public audience at the Grand Cafe","answer":"the Lumi\u00e8re brothers","value":2000,"daily_double":false,"type":"text"}]},{"name":"THE DEL-TONES","questions":[{"clue":null,"answer":null,"value":null,"daily_double":false},{"clue":"Del Shannon wondered in 1961 why--why, why, why, why, why \"my little\" this title person took off","answer":"Runaway","value":800,"daily_double":false,"type":"text"},{"clue":"Del the Funky Homosapien is a cousin of this \"cool\" rapper of N.W.A. fame","answer":"Ice Cube","value":1200,"daily_double":false,"type":"text"},{"clue":"This title woman in a 1997 Tarantino film chooses to play the Delfonics during a scene with Robert Forster","answer":"Jackie Brown","value":1600,"daily_double":false,"type":"text"},{"clue":"Perhaps finding it a \"Cruel World\", in 2014 she unleashed a bit of the old \"Ultraviolence\"","answer":"Lana Del Rey","value":2000,"daily_double":false,"type":"text"}]}],"final":{"category":"LITTLE COUNTRIES","clue":"It's the closest nation to the mainland U.S. where cars customarily drive on the left","answer":"the Bahamas"}}